Anteater_GH/__init__.py
Anteater_GH/fuzzers.py
anteater_gh-0.0.1.dist-info/METADATA
anteater_gh-0.0.1.dist-info/WHEEL
anteater_gh-0.0.1.dist-info/licenses/LICENSE.md
anteater_gh-0.0.1.dist-info/RECORD
