Metadata-Version: 2.3
Name: Anteater_GH
Version: 0.0.1
Summary: Fuzz testing helper functions for Grasshopper Pythons.
Project-URL: Homepage, https://github.com/JamesParrott/Anteater_GH
Project-URL: Bug Tracker, https://github.com/JamesParrott/Anteater_GH/issues
Author-email: James Parrott <james.parrott@proton.me>
License: 
License-File: LICENSE.md
Keywords: Grasshopper,Rhino,fuzzing,testing
Classifier: Programming Language :: Python
Classifier: Programming Language :: Python :: 2
Classifier: Programming Language :: Python :: 3
Classifier: Programming Language :: Python :: Implementation :: IronPython
Requires-Python: >=2.7
